slsne/__init__.py
slsne/lcurve.py
slsne/models.py
slsne/mosutils.py
slsne/plots.py
slsne/utils.py
slsne/ref_data/aguilera-dena.txt
slsne/ref_data/all_parameters.txt
slsne/ref_data/boom_mesh.npz
slsne/ref_data/filter_reference.txt
slsne/ref_data/generic_reference.txt
slsne/ref_data/kumar.txt
slsne/ref_data/peak_mesh.npz
slsne/ref_data/references.bib
slsne/ref_data/sne_data.txt
slsne/ref_data/use_names.txt
slsne/ref_data/extrabol/2005ap.txt
slsne/ref_data/extrabol/2007bi.txt
slsne/ref_data/extrabol/2010gx.txt
slsne/ref_data/extrabol/2010kd.txt
slsne/ref_data/extrabol/2010md.txt
slsne/ref_data/extrabol/2011ke.txt
slsne/ref_data/extrabol/2011kg.txt
slsne/ref_data/extrabol/2012il.txt
slsne/ref_data/extrabol/2013dg.txt
slsne/ref_data/extrabol/2015bn.txt
slsne/ref_data/extrabol/2016eay.txt
slsne/ref_data/extrabol/2016inl.txt
slsne/ref_data/extrabol/2017dwh.txt
slsne/ref_data/extrabol/2017egm.txt
slsne/ref_data/extrabol/2017ens.txt
slsne/ref_data/extrabol/2017gci.txt
slsne/ref_data/extrabol/2018avk.txt
slsne/ref_data/extrabol/2018bgv.txt
slsne/ref_data/extrabol/2018bsz.txt
slsne/ref_data/extrabol/2018bym.txt
slsne/ref_data/extrabol/2018cxa.txt
slsne/ref_data/extrabol/2018ffj.txt
slsne/ref_data/extrabol/2018ffs.txt
slsne/ref_data/extrabol/2018hpq.txt
slsne/ref_data/extrabol/2018kyt.txt
slsne/ref_data/extrabol/2018lfd.txt
slsne/ref_data/extrabol/2018lfe.txt
slsne/ref_data/extrabol/2018lzx.txt
slsne/ref_data/extrabol/2019aamp.txt
slsne/ref_data/extrabol/2019aamq.txt
slsne/ref_data/extrabol/2019aams.txt
slsne/ref_data/extrabol/2019aamt.txt
slsne/ref_data/extrabol/2019aamu.txt
slsne/ref_data/extrabol/2019aamv.txt
slsne/ref_data/extrabol/2019aamx.txt
slsne/ref_data/extrabol/2019bgu.txt
slsne/ref_data/extrabol/2019cca.txt
slsne/ref_data/extrabol/2019cdt.txt
slsne/ref_data/extrabol/2019cwu.txt
slsne/ref_data/extrabol/2019dgr.txt
slsne/ref_data/extrabol/2019dlr.txt
slsne/ref_data/extrabol/2019enz.txt
slsne/ref_data/extrabol/2019eot.txt
slsne/ref_data/extrabol/2019gfm.txt
slsne-0.2.dist-info/LICENSE.md
slsne-0.2.dist-info/METADATA
slsne-0.2.dist-info/WHEEL
slsne-0.2.dist-info/top_level.txt
slsne-0.2.dist-info/RECORD
